cameraservice/__init__.py
cameraservice/services/__init__.py
cameraservice/services/cameras/__init__.py
cameraservice/services/cameras/camera_provider.py
cameraservice/services/cameras/camera_service_api.py
cameraservice/services/cameras/constants.py
cameraservice/services/cameras/models.py
cameraservice/services/grpc/__init__.py
cameraservice/services/grpc/camera_service_pb2.py
cameraservice/services/grpc/camera_service_pb2.pyi
cameraservice/services/grpc/camera_service_pb2_grpc.py
cameraservice/services/grpc/grpcutilsc.py
cameraservice/services/grpc/grpcutilss.py
cameraservice/services/grpc/pb2utils.py
cameraservice/util/__init__.py
cameraservice/util/exceptions.py
cameraservice/util/jsonencoder.py
cameraservice/util/syncutils.py
cameraservice/util/utils.py
camera_service_api-1.5.dist-info/METADATA
camera_service_api-1.5.dist-info/WHEEL
camera_service_api-1.5.dist-info/top_level.txt
camera_service_api-1.5.dist-info/RECORD
