Metadata-Version: 2.1
Name: camera-service-api
Version: 1.5
Summary: Camera service grpc api
Home-page: 
Author: L.K
Author-email: L.K@idontwant.com
Classifier: Programming Language :: Python :: 3
Classifier: Topic :: Software Development :: Libraries :: Python Modules
Classifier: Operating System :: POSIX :: Linux
Requires-Python: >=3.7
Requires-Dist: grpcio
Requires-Dist: protobuf
